{
  "type": "pfm:dynamic_furniture",
  "group": "kitchen",
  "supportedVariants": [
    "minecraft:oak",
    "minecraft:bamboo",
    "minecraft:spruce",
    "minecraft:birch",
    "minecraft:jungle",
    "minecraft:acacia",
    "minecraft:cherry",
    "minecraft:dark_oak",
    "minecraft:mangrove",
    "minecraft:crimson",
    "minecraft:warped",
    "cataclysm:chorus",
    "unearthed_journey:glyptostrobus",
    "unearthed_journey:ginkgo",
    "unearthed_journey:nothofagus",
    "unearthed_journey:taxodium",
    "unearthed_journey:dead",
    "unearthed_journey:fig",
    "unearthed_journey:palaeoraphe",
    "unearthed_journey:black_walnut",
    "unearthed_journey:sabalites",
    "unearthed_journey:metasequoia_heerii",
    "unearthed_journey:pine",
    "unearthed_journey:acaciapollenites",
    "unearthed_journey:leguminocarpon",
    "unearthed_journey:betula",
    "unearthed_journey:mangaris",
    "biomemakeover:blighted_balsa",
    "biomemakeover:willow",
    "biomemakeover:swamp_cypress",
    "biomemakeover:ancient_oak",
    "minecraft:stone",
    "minecraft:calcite",
    "minecraft:light_wood",
    "minecraft:dark_wood",
    "minecraft:pink_wood",
    "minecraft:netherite",
    "minecraft:granite",
    "minecraft:diorite",
    "minecraft:andesite",
    "minecraft:basalt",
    "minecraft:blackstone",
    "minecraft:deepslate",
    "unusualend:gneiss",
    "unusualend:gloopstone",
    "unusualend:gloopslate",
    "unusualend:warped_stone",
    "samurai_dynasty:spirit_stone",
    "cataclysm:end_stone",
    "cataclysm:obsidian",
    "cataclysm:sandstone",
    "cataclysm:azure_seastone",
    "unearthed_journey:palagonite",
    "unearthed_journey:breccia",
    "unearthed_journey:archstone",
    "unearthed_journey:bituminous_rock",
    "biomemakeover:mesmerite",
    ":dark_concrete",
    ":concrete",
    ":smooth_stone",
    ":deepslate_tile",
    ":granite_terracotta",
    ":andesite_oak",
    ":deepslate_dark_oak",
    ":blackstone_crimson"
  ],
  "ingredients": {
    "vanillaIngredients": [
      {
        "item": "minecraft:chest"
      }
    ],
    "variantChildren": {
      "secondary": 3,
      "base": 5
    }
  },
  "result": {
    "outputClass": "KitchenDrawerBlock"
  }
}